hellow_world_francois/__init__.py
hellow_world_francois/hellow.py
hellow_world_francois-0.1.1.dist-info/WHEEL
hellow_world_francois-0.1.1.dist-info/METADATA
hellow_world_francois-0.1.1.dist-info/RECORD
